{
    "1": {
        "name": "Básico-limitado ciudad sin estacionamiento",
        "situations": {
            "N1": {
                "S1": "C1-S1",
                "S2": "C1-S2"
            },
            "N2": {
                "S1": "C2-S1",
                "S2": "C2-S2",
                "S3": "C2-S3"
            },
            "N4": {
                "S1": {
                    "CC": [
                        "C4-S1-CCA",
                        "C4-S1-CCB"
                    ],
                    "TAM": [
                        "C4-S1-TAMA",
                        "C4-S1-TAMB"
                    ],
                    "FT": [
                        "C4-S1-FTA",
                        "C4-S1-FTB",
                        "C4-S1-FTC"
                    ],
                    "CCA": [
                        "C4-S1-CCAA",
                        "C4-S1-CCAB",
                        "C4-S1-CCAC"
                    ],
                    "OC": [
                        "C4-S1-OCA",
                        "C4-S1-OCB",
                        "C4-S1-OCC"
                    ],
                    "OT": [
                        "C4-S1-OTA",
                        "C4-S1-OTB",
                        "C4-S1-OTC",
                        "C4-S1-OTD"
                    ]
                }
            }
        },
        "greatest_anxiety": [
            "C4-S1-FTC",
            "C4-S1-CCAB",
            "C4-S1-OCA",
            "C4-S1-OCC",
            "C4-S1-OTA",
            "C4-S1-OTB",
            "C4-S1-OTC",
            "C4-S1-OTD"
        ]
    },
    "2": {
        "name": "Básico-limitado ciudad",
        "situations": {
            "N1": {
                "S1": "C1-S1",
                "S2": "C1-S2"
            },
            "N2": {
                "S1": "C2-S1",
                "S2": "C2-S2",
                "S3": "C2-S3"
            },
            "N3": {
                "S1": {
                    "PC": [
                        "C3-S1-PCA",
                        "C3-S1-PCB",
                        "C3-S1-PCC"
                    ]
                },
                "S2": {
                    "PS": [
                        "C3-S2-PSA",
                        "C3-S2-PSB",
                        "C3-S2-PSC",
                        "C3-S2-PSD",
                        "C3-S2-PSE"
                    ]
                }
            },
            "N4": {
                "S1": {
                    "CC": [
                        "C4-S1-CCA",
                        "C4-S1-CCB"
                    ],
                    "TAM": [
                        "C4-S1-TAMA",
                        "C4-S1-TAMB"
                    ],
                    "FT": [
                        "C4-S1-FTA",
                        "C4-S1-FTB",
                        "C4-S1-FTC"
                    ],
                    "CCA": [
                        "C4-S1-CCAA",
                        "C4-S1-CCAB",
                        "C4-S1-CCAC"
                    ],
                    "OC": [
                        "C4-S1-OCA",
                        "C4-S1-OCB",
                        "C4-S1-OCC"
                    ],
                    "OT": [
                        "C4-S1-OTA",
                        "C4-S1-OTB",
                        "C4-S1-OTC",
                        "C4-S1-OTD"
                    ]
                }
            }
        },
        "greatest_anxiety": [
            "C3-S2-PSE",
            "C4-S1-FTC",
            "C4-S1-CCAB",
            "C4-S1-OCA",
            "C4-S1-OCC",
            "C4-S1-OTA",
            "C4-S1-OTB",
            "C4-S1-OTC",
            "C4-S1-OTD"
        ]
    },
    "3": {
        "name": "Básico ciudad sin estacionamiento",
        "situations": {
            "N1": {
                "S1": "C1-S1",
                "S2": "C1-S2"
            },
            "N2": {
                "S1": "C2-S1",
                "S2": "C2-S2",
                "S3": "C2-S3"
            },
            "N4": {
                "S1": {
                    "CC": [
                        "C4-S1-CCA",
                        "C4-S1-CCB"
                    ],
                    "TAM": [
                        "C4-S1-TAMA",
                        "C4-S1-TAMB"
                    ],
                    "FT": [
                        "C4-S1-FTA",
                        "C4-S1-FTB",
                        "C4-S1-FTC"
                    ],
                    "CT": [
                        "C4-S1-CTA",
                        "C4-S1-CTB",
                        "C4-S1-CTC",
                        "C4-S1-CTD"
                    ],
                    "CCA": [
                        "C4-S1-CCAA",
                        "C4-S1-CCAB",
                        "C4-S1-CCAC"
                    ],
                    "OC": [
                        "C4-S1-OCA",
                        "C4-S1-OCB",
                        "C4-S1-OCC"
                    ],
                    "OT": [
                        "C4-S1-OTA",
                        "C4-S1-OTB",
                        "C4-S1-OTC",
                        "C4-S1-OTD"
                    ]
                }
            }
        },
        "greatest_anxiety": [
            "C4-S1-TAMB",
            "C4-S1-FTC",
            "C4-S1-CCAB",
            "C4-S1-OCA",
            "C4-S1-OCC",
            "C4-S1-OTA",
            "C4-S1-OTB",
            "C4-S1-OTC",
            "C4-S1-OTD"
        ]
    },
    "4": {
        "name": "Básico ciudad",
        "situations": {
            "N1": {
                "S1": "C1-S1",
                "S2": "C1-S2"
            },
            "N2": {
                "S1": "C2-S1",
                "S2": "C2-S2",
                "S3": "C2-S3"
            },
            "N3": {
                "S1": {
                    "PC": [
                        "C3-S1-PCA",
                        "C3-S1-PCB",
                        "C3-S1-PCC"
                    ]
                },
                "S2": {
                    "PS": [
                        "C3-S2-PSA",
                        "C3-S2-PSB",
                        "C3-S2-PSC",
                        "C3-S2-PSD",
                        "C3-S2-PSE"
                    ]
                }
            },
            "N4": {
                "S1": {
                    "CC": [
                        "C4-S1-CCA",
                        "C4-S1-CCB"
                    ],
                    "TAM": [
                        "C4-S1-TAMA",
                        "C4-S1-TAMB"
                    ],
                    "FT": [
                        "C4-S1-FTA",
                        "C4-S1-FTB",
                        "C4-S1-FTC"
                    ],
                    "CT": [
                        "C4-S1-CTA",
                        "C4-S1-CTB",
                        "C4-S1-CTC",
                        "C4-S1-CTD"
                    ],
                    "CCA": [
                        "C4-S1-CCAA",
                        "C4-S1-CCAB",
                        "C4-S1-CCAC"
                    ],
                    "OC": [
                        "C4-S1-OCA",
                        "C4-S1-OCB",
                        "C4-S1-OCC"
                    ],
                    "OT": [
                        "C4-S1-OTA",
                        "C4-S1-OTB",
                        "C4-S1-OTC",
                        "C4-S1-OTD"
                    ]
                }
            }
        },
        "greatest_anxiety": [
            "C3-S2-PSE",
            "C4-S1-TAMB",
            "C4-S1-FTC",
            "C4-S1-CCAB",
            "C4-S1-OCA",
            "C4-S1-OCC",
            "C4-S1-OTA",
            "C4-S1-OTB",
            "C4-S1-OTC",
            "C4-S1-OTD"
        ]
    },
    "5": {
        "name": "Básico-limitado completo sin estacionamiento",
        "situations": {
            "N1": {
                "S1": "C1-S1",
                "S2": "C1-S2"
            },
            "N2": {
                "S1": "C2-S1",
                "S2": "C2-S2",
                "S3": "C2-S3"
            },
            "N4": {
                "S1": {
                    "CC": [
                        "C4-S1-CCA",
                        "C4-S1-CCB"
                    ],
                    "TAM": [
                        "C4-S1-TAMA",
                        "C4-S1-TAMB"
                    ],
                    "FT": [
                        "C4-S1-FTA",
                        "C4-S1-FTB",
                        "C4-S1-FTC"
                    ],
                    "CCA": [
                        "C4-S1-CCAA",
                        "C4-S1-CCAB",
                        "C4-S1-CCAC"
                    ],
                    "OC": [
                        "C4-S1-OCA",
                        "C4-S1-OCB",
                        "C4-S1-OCC"
                    ],
                    "OT": [
                        "C4-S1-OTA",
                        "C4-S1-OTB",
                        "C4-S1-OTC",
                        "C4-S1-OTD"
                    ]
                }
            },
            "N5": {
                "S2": {
                    "CC": [
                        "C4-S2-CCA",
                        "C4-S2-CCB"
                    ],
                    "TV": [
                        "C4-S2-TVA",
                        "C4-S2-TVB",
                        "C4-S2-TVC"
                    ],
                    "CCA": [
                        "C4-S2-CCAA",
                        "C4-S2-CCAB",
                        "C4-S2-CCAC",
                        "C4-S2-CCAD"
                    ],
                    "FT": [
                        "C4-S2-FTA",
                        "C4-S2-FTB",
                        "C4-S2-FTC"
                    ],
                    "OC": [
                        "C4-S2-OCA",
                        "C4-S2-OCB",
                        "C4-S2-OCC"
                    ],
                    "OT": [
                        "C4-S2-OTA",
                        "C4-S2-OTB",
                        "C4-S2-OTC",
                        "C4-S2-OTD",
                        "C4-S2-OTE",
                        "C4-S2-OTF",
                        "C4-S2-OTG"
                    ]
                }
            }
        },
        "greatest_anxiety": [
            "C4-S2-CCB",
            "C4-S2-FTC",
            "C4-S2-OCA",
            "C4-S2-OCC",
            "C4-S2-OTA",
            "C4-S2-OTB",
            "C4-S2-OTC",
            "C4-S2-OTD",
            "C4-S2-OTE",
            "C4-S2-OTF",
            "C4-S2-OTG"
        ]
    },
    "6": {
        "name": "Básico-limitado completo",
        "situations": {
            "N1": {
                "S1": "C1-S1",
                "S2": "C1-S2"
            },
            "N2": {
                "S1": "C2-S1",
                "S2": "C2-S2",
                "S3": "C2-S3"
            },
            "N3": {
                "S1": {
                    "PC": [
                        "C3-S1-PCA",
                        "C3-S1-PCB",
                        "C3-S1-PCC"
                    ]
                },
                "S2": {
                    "PS": [
                        "C3-S2-PSA",
                        "C3-S2-PSB",
                        "C3-S2-PSC",
                        "C3-S2-PSD",
                        "C3-S2-PSE"
                    ]
                }
            },
            "N4": {
                "S1": {
                    "CC": [
                        "C4-S1-CCA",
                        "C4-S1-CCB"
                    ],
                    "TAM": [
                        "C4-S1-TAMA",
                        "C4-S1-TAMB"
                    ],
                    "FT": [
                        "C4-S1-FTA",
                        "C4-S1-FTB",
                        "C4-S1-FTC"
                    ],
                    "CCA": [
                        "C4-S1-CCAA",
                        "C4-S1-CCAB",
                        "C4-S1-CCAC"
                    ],
                    "OC": [
                        "C4-S1-OCA",
                        "C4-S1-OCB",
                        "C4-S1-OCC"
                    ],
                    "OT": [
                        "C4-S1-OTA",
                        "C4-S1-OTB",
                        "C4-S1-OTC",
                        "C4-S1-OTD"
                    ]
                }
            },
            "N5": {
                "S2": {
                    "CC": [
                        "C4-S2-CCA",
                        "C4-S2-CCB"
                    ],
                    "TV": [
                        "C4-S2-TVA",
                        "C4-S2-TVB",
                        "C4-S2-TVC"
                    ],
                    "CCA": [
                        "C4-S2-CCAA",
                        "C4-S2-CCAB",
                        "C4-S2-CCAC",
                        "C4-S2-CCAD"
                    ],
                    "FT": [
                        "C4-S2-FTA",
                        "C4-S2-FTB",
                        "C4-S2-FTC"
                    ],
                    "OC": [
                        "C4-S2-OCA",
                        "C4-S2-OCB",
                        "C4-S2-OCC"
                    ],
                    "OT": [
                        "C4-S2-OTA",
                        "C4-S2-OTB",
                        "C4-S2-OTC",
                        "C4-S2-OTD",
                        "C4-S2-OTE",
                        "C4-S2-OTF",
                        "C4-S2-OTG"
                    ]
                }
            }
        },
        "greatest_anxiety": [
            "C3-S2-PSE",
            "C4-S2-CCB",
            "C4-S2-FTC",
            "C4-S2-OCA",
            "C4-S2-OCC",
            "C4-S2-OTA",
            "C4-S2-OTB",
            "C4-S2-OTC",
            "C4-S2-OTD",
            "C4-S2-OTE",
            "C4-S2-OTF",
            "C4-S2-OTG"
        ]
    },
    "7": {
        "name": "Básico completo sin estacionamiento",
        "situations": {
            "N1": {
                "S1": "C1-S1",
                "S2": "C1-S2"
            },
            "N2": {
                "S1": "C2-S1",
                "S2": "C2-S2",
                "S3": "C2-S3"
            },
            "N4": {
                "S1": {
                    "CC": [
                        "C4-S1-CCA",
                        "C4-S1-CCB"
                    ],
                    "TAM": [
                        "C4-S1-TAMA",
                        "C4-S1-TAMB"
                    ],
                    "FT": [
                        "C4-S1-FTA",
                        "C4-S1-FTB",
                        "C4-S1-FTC"
                    ],
                    "CT": [
                        "C4-S1-CTA",
                        "C4-S1-CTB",
                        "C4-S1-CTC",
                        "C4-S1-CTD"
                    ],
                    "CCA": [
                        "C4-S1-CCAA",
                        "C4-S1-CCAB",
                        "C4-S1-CCAC"
                    ],
                    "OC": [
                        "C4-S1-OCA",
                        "C4-S1-OCB",
                        "C4-S1-OCC"
                    ],
                    "OT": [
                        "C4-S1-OTA",
                        "C4-S1-OTB",
                        "C4-S1-OTC",
                        "C4-S1-OTD"
                    ]
                }
            },
            "N5": {
                "S2": {
                    "CC": [
                        "C4-S2-CCA",
                        "C4-S2-CCB"
                    ],
                    "TV": [
                        "C4-S2-TVA",
                        "C4-S2-TVB",
                        "C4-S2-TVC"
                    ],
                    "CCA": [
                        "C4-S2-CCAA",
                        "C4-S2-CCAB",
                        "C4-S2-CCAC",
                        "C4-S2-CCAD"
                    ],
                    "FT": [
                        "C4-S2-FTA",
                        "C4-S2-FTB",
                        "C4-S2-FTC"
                    ],
                    "CT": [
                        "C4-S2-CTA",
                        "C4-S2-CTB",
                        "C4-S2-CTC",
                        "C4-S2-CTD"
                    ],
                    "OC": [
                        "C4-S2-OCA",
                        "C4-S2-OCB",
                        "C4-S2-OCC"
                    ],
                    "OT": [
                        "C4-S2-OTA",
                        "C4-S2-OTB",
                        "C4-S2-OTC",
                        "C4-S2-OTD",
                        "C4-S2-OTE",
                        "C4-S2-OTF",
                        "C4-S2-OTG"
                    ]
                }
            }
        },
        "greatest_anxiety": [
            "C4-S2-CCB",
            "C4-S2-CTB",
            "C4-S2-CCAC",
            "C4-S2-FTC",
            "C4-S2-OCA",
            "C4-S2-OCC",
            "C4-S2-OTA",
            "C4-S2-OTB",
            "C4-S2-OTC",
            "C4-S2-OTD",
            "C4-S2-OTE",
            "C4-S2-OTF",
            "C4-S2-OTG"
        ]
    },
    "8": {
        "name": "Básico completo",
        "situations": {
            "N1": {
                "S1": "C1-S1",
                "S2": "C1-S2"
            },
            "N2": {
                "S1": "C2-S1",
                "S2": "C2-S2",
                "S3": "C2-S3"
            },
            "N3": {
                "S1": {
                    "PC": [
                        "C3-S1-PCA",
                        "C3-S1-PCB",
                        "C3-S1-PCC"
                    ]
                },
                "S2": {
                    "PS": [
                        "C3-S2-PSA",
                        "C3-S2-PSB",
                        "C3-S2-PSC",
                        "C3-S2-PSD",
                        "C3-S2-PSE"
                    ]
                }
            },
            "N4": {
                "S1": {
                    "CC": [
                        "C4-S1-CCA",
                        "C4-S1-CCB"
                    ],
                    "TAM": [
                        "C4-S1-TAMA",
                        "C4-S1-TAMB"
                    ],
                    "FT": [
                        "C4-S1-FTA",
                        "C4-S1-FTB",
                        "C4-S1-FTC"
                    ],
                    "CT": [
                        "C4-S1-CTA",
                        "C4-S1-CTB",
                        "C4-S1-CTC",
                        "C4-S1-CTD"
                    ],
                    "CCA": [
                        "C4-S1-CCAA",
                        "C4-S1-CCAB",
                        "C4-S1-CCAC"
                    ],
                    "OC": [
                        "C4-S1-OCA",
                        "C4-S1-OCB",
                        "C4-S1-OCC"
                    ],
                    "OT": [
                        "C4-S1-OTA",
                        "C4-S1-OTB",
                        "C4-S1-OTC",
                        "C4-S1-OTD"
                    ]
                }
            },
            "N5": {
                "S2": {
                    "CC": [
                        "C4-S2-CCA",
                        "C4-S2-CCB"
                    ],
                    "TV": [
                        "C4-S2-TVA",
                        "C4-S2-TVB",
                        "C4-S2-TVC"
                    ],
                    "CCA": [
                        "C4-S2-CCAA",
                        "C4-S2-CCAB",
                        "C4-S2-CCAC",
                        "C4-S2-CCAD"
                    ],
                    "FT": [
                        "C4-S2-FTA",
                        "C4-S2-FTB",
                        "C4-S2-FTC"
                    ],
                    "CT": [
                        "C4-S2-CTA",
                        "C4-S2-CTB",
                        "C4-S2-CTC",
                        "C4-S2-CTD"
                    ],
                    "OC": [
                        "C4-S2-OCA",
                        "C4-S2-OCB",
                        "C4-S2-OCC"
                    ],
                    "OT": [
                        "C4-S2-OTA",
                        "C4-S2-OTB",
                        "C4-S2-OTC",
                        "C4-S2-OTD",
                        "C4-S2-OTE",
                        "C4-S2-OTF",
                        "C4-S2-OTG"
                    ]
                }
            }
        },
        "greatest_anxiety": [
            "C3-S2-PSE",
            "C4-S2-CCB",
            "C4-S2-CTB",
            "C4-S2-CCAC",
            "C4-S2-FTC",
            "C4-S2-OCA",
            "C4-S2-OCC",
            "C4-S2-OTA",
            "C4-S2-OTB",
            "C4-S2-OTC",
            "C4-S2-OTD",
            "C4-S2-OTE",
            "C4-S2-OTF",
            "C4-S2-OTG"
        ]
    },
    "9": {
        "name": "Avanzado sin estacionamiento",
        "situations": {
            "N1": {
                "S1": "C1-S1",
                "S2": "C1-S2"
            },
            "N2": {
                "S1": "C2-S1",
                "S2": "C2-S2",
                "S3": "C2-S3"
            },
            "N4": {
                "S1": {
                    "CON": [
                        "C4-S1-CONA",
                        "C4-S1-CONB"
                    ],
                    "CC": [
                        "C4-S1-CCA",
                        "C4-S1-CCB"
                    ],
                    "TAM": [
                        "C4-S1-TAMA",
                        "C4-S1-TAMB"
                    ],
                    "FT": [
                        "C4-S1-FTA",
                        "C4-S1-FTB",
                        "C4-S1-FTC"
                    ],
                    "CT": [
                        "C4-S1-CTA",
                        "C4-S1-CTB",
                        "C4-S1-CTC",
                        "C4-S1-CTD"
                    ],
                    "OT": [
                        "C4-S1-OTA",
                        "C4-S1-OTB",
                        "C4-S1-OTC",
                        "C4-S1-OTD"
                    ]
                }
            },
            "N5": {
                "S2": {
                    "CON": [
                        "C4-S2-CONA",
                        "C4-S2-CONB"
                    ],
                    "CC": [
                        "C4-S2-CCA",
                        "C4-S2-CCB"
                    ],
                    "TV": [
                        "C4-S2-TVA",
                        "C4-S2-TVB",
                        "C4-S2-TVC"
                    ],
                    "CCA": [
                        "C4-S2-CCAA",
                        "C4-S2-CCAB",
                        "C4-S2-CCAC",
                        "C4-S2-CCAD"
                    ],
                    "FT": [
                        "C4-S2-FTA",
                        "C4-S2-FTB",
                        "C4-S2-FTC"
                    ],
                    "CT": [
                        "C4-S2-CTA",
                        "C4-S2-CTB",
                        "C4-S2-CTC",
                        "C4-S2-CTD"
                    ],
                    "OC": [
                        "C4-S2-OCA",
                        "C4-S2-OCB",
                        "C4-S2-OCC"
                    ],
                    "OT": [
                        "C4-S2-OTA",
                        "C4-S2-OTB",
                        "C4-S2-OTC",
                        "C4-S2-OTD",
                        "C4-S2-OTE",
                        "C4-S2-OTF",
                        "C4-S2-OTG"
                    ]
                }
            }
        },
        "greatest_anxiety": [
            "C4-S2-CONB",
            "C4-S2-CCB",
            "C4-S2-CTB",
            "C4-S2-CCAC",
            "C4-S2-FTC",
            "C4-S2-OCA",
            "C4-S2-OCC",
            "C4-S2-OTA",
            "C4-S2-OTB",
            "C4-S2-OTC",
            "C4-S2-OTD",
            "C4-S2-OTE",
            "C4-S2-OTF",
            "C4-S2-OTG"
        ]
    },
    "10": {
        "name": "Avazando completo",
        "situations": {
            "N1": {
                "S1": "C1-S1",
                "S2": "C1-S2"
            },
            "N2": {
                "S1": "C2-S1",
                "S2": "C2-S2",
                "S3": "C2-S3"
            },
            "N3": {
                "S1": {
                    "PC": [
                        "C3-S1-PCB",
                        "C3-S1-PCC"
                    ]
                },
                "S2": {
                    "PS": [
                        "C3-S2-PSC",
                        "C3-S2-PSD",
                        "C3-S2-PSE"
                    ]
                }
            },
            "N4": {
                "S1": {
                    "CON": [
                        "C4-S1-CONA",
                        "C4-S1-CONB"
                    ],
                    "CC": [
                        "C4-S1-CCA",
                        "C4-S1-CCB"
                    ],
                    "TAM": [
                        "C4-S1-TAMA",
                        "C4-S1-TAMB"
                    ],
                    "FT": [
                        "C4-S1-FTA",
                        "C4-S1-FTB",
                        "C4-S1-FTC"
                    ],
                    "CT": [
                        "C4-S1-CTA",
                        "C4-S1-CTB",
                        "C4-S1-CTC",
                        "C4-S1-CTD"
                    ],
                    "OT": [
                        "C4-S1-OTA",
                        "C4-S1-OTB",
                        "C4-S1-OTC",
                        "C4-S1-OTD"
                    ]
                }
            },
            "N5": {
                "S2": {
                    "CON": [
                        "C4-S2-CONA",
                        "C4-S2-CONB"
                    ],
                    "CC": [
                        "C4-S2-CCA",
                        "C4-S2-CCB"
                    ],
                    "TV": [
                        "C4-S2-TVA",
                        "C4-S2-TVB",
                        "C4-S2-TVC"
                    ],
                    "CCA": [
                        "C4-S2-CCAA",
                        "C4-S2-CCAB",
                        "C4-S2-CCAC",
                        "C4-S2-CCAD"
                    ],
                    "FT": [
                        "C4-S2-FTA",
                        "C4-S2-FTB",
                        "C4-S2-FTC"
                    ],
                    "CT": [
                        "C4-S2-CTA",
                        "C4-S2-CTB",
                        "C4-S2-CTC",
                        "C4-S2-CTD"
                    ],
                    "OC": [
                        "C4-S2-OCA",
                        "C4-S2-OCB",
                        "C4-S2-OCC"
                    ],
                    "OT": [
                        "C4-S2-OTA",
                        "C4-S2-OTB",
                        "C4-S2-OTC",
                        "C4-S2-OTD",
                        "C4-S2-OTE",
                        "C4-S2-OTF",
                        "C4-S2-OTG"
                    ]
                }
            }
        },
        "greatest_anxiety": [
            "C4-S2-CONB",
            "C4-S2-CCB",
            "C4-S2-CTB",
            "C4-S2-CCAC",
            "C4-S2-FTC",
            "C4-S2-OCA",
            "C4-S2-OCC",
            "C4-S2-OTA",
            "C4-S2-OTB",
            "C4-S2-OTC",
            "C4-S2-OTD",
            "C4-S2-OTE",
            "C4-S2-OTF",
            "C4-S2-OTG"
        ]
    },
    "11": {
        "name": "Avazando completo + adelantamiento",
        "situations": {
            "N1": {
                "S1": "C1-S1",
                "S2": "C1-S2"
            },
            "N2": {
                "S1": "C2-S1",
                "S2": "C2-S2",
                "S3": "C2-S3"
            },
            "N3": {
                "S1": {
                    "PC": [
                        "C3-S1-PCB",
                        "C3-S1-PCC"
                    ]
                },
                "S2": {
                    "PS": [
                        "C3-S2-PSC",
                        "C3-S2-PSD",
                        "C3-S2-PSE"
                    ]
                }
            },
            "N4": {
                "S1": {
                    "CON": [
                        "C4-S1-CONA",
                        "C4-S1-CONB"
                    ],
                    "CC": [
                        "C4-S1-CCA",
                        "C4-S1-CCB"
                    ],
                    "TAM": [
                        "C4-S1-TAMA",
                        "C4-S1-TAMB"
                    ],
                    "FT": [
                        "C4-S1-FTA",
                        "C4-S1-FTB",
                        "C4-S1-FTC"
                    ],
                    "CT": [
                        "C4-S1-CTA",
                        "C4-S1-CTB",
                        "C4-S1-CTC",
                        "C4-S1-CTD"
                    ],
                    "OT": [
                        "C4-S1-OTA",
                        "C4-S1-OTB",
                        "C4-S1-OTC",
                        "C4-S1-OTD"
                    ]
                }
            },
            "N5": {
                "S2": {
                    "CON": [
                        "C4-S2-CONA",
                        "C4-S2-CONB"
                    ],
                    "CC": [
                        "C4-S2-CCA",
                        "C4-S2-CCB"
                    ],
                    "TV": [
                        "C4-S2-TVA",
                        "C4-S2-TVB",
                        "C4-S2-TVC"
                    ],
                    "CCA": [
                        "C4-S2-CCAA",
                        "C4-S2-CCAB",
                        "C4-S2-CCAC",
                        "C4-S2-CCAD"
                    ],
                    "FT": [
                        "C4-S2-FTA",
                        "C4-S2-FTB",
                        "C4-S2-FTC"
                    ],
                    "CT": [
                        "C4-S2-CTA",
                        "C4-S2-CTB",
                        "C4-S2-CTC",
                        "C4-S2-CTD"
                    ],
                    "OC": [
                        "C4-S2-OCA",
                        "C4-S2-OCB",
                        "C4-S2-OCC"
                    ],
                    "OT": [
                        "C4-S2-OTA",
                        "C4-S2-OTB",
                        "C4-S2-OTC",
                        "C4-S2-OTD",
                        "C4-S2-OTE",
                        "C4-S2-OTF",
                        "C4-S2-OTG"
                    ]
                }
            },
            "N6": {
                "S1": {
                    "VA": [
                        "C5-S1-VAA",
                        "C5-S1-VAB",
                        "C5-S1-VAC",
                        "C5-S1-VAD",
                        "C5-S1-VAE"
                    ],
                    "FT": [
                        "C5-S1-FTA",
                        "C5-S1-FTB",
                        "C5-S1-FTC"
                    ],
                    "CT": [
                        "C5-S1-CTA",
                        "C5-S1-CTB",
                        "C5-S1-CTC",
                        "C5-S1-CTD"
                    ],
                    "OC": [
                        "C5-S1-OCA",
                        "C5-S1-OCB",
                        "C5-S1-OCC"
                    ]
                }
            },
            "N7": {
                "S2": {
                    "VA": [
                        "C5-S2-VAA",
                        "C5-S2-VAB",
                        "C5-S2-VAC",
                        "C5-S2-VAD",
                        "C5-S2-VAE"
                    ],
                    "FT": [
                        "C5-S2-FTA",
                        "C5-S2-FTB",
                        "C5-S2-FTC"
                    ],
                    "CT": [
                        "C5-S2-CTA",
                        "C5-S2-CTB",
                        "C5-S2-CTC",
                        "C5-S2-CTD"
                    ],
                    "OC": [
                        "C5-S2-OCA",
                        "C5-S2-OCB",
                        "C5-S2-OCC"
                    ],
                    "OT": [
                        "C5-S2-OTA"
                    ]
                }
            }
        },
        "greatest_anxiety": [
            "C4-S2-CCB",
            "C4-S2-CTB",
            "C4-S2-CCAC",
            "C4-S2-FTC",
            "C4-S2-OCA",
            "C4-S2-OCC",
            "C4-S2-OTA",
            "C4-S2-OTB",
            "C4-S2-OTC",
            "C4-S2-OTD",
            "C4-S2-OTE",
            "C4-S2-OTF",
            "C4-S2-OTG",
            "C5-S2-CCB",
            "C5-S2-VAC",
            "C5-S2-VAE",
            "C5-S2-CCAB",
            "C5-S2-CCAC",
            "C5-S2-FTC",
            "C5-S2-CTB",
            "C5-S2-OCA",
            "C5-S2-OCC",
            "C5-S2-OTA"
        ]
    }
}